[
  {
    "cluster": "misc_articles",
    "original": "Approaching_the_Infinite.html",
    "status": "processed"
  },
  {
    "cluster": "misc_articles",
    "original": "Lord_of_the_Cows.html",
    "status": "processed"
  },
  {
    "cluster": "misc_articles",
    "original": ".html",
    "status": "processed"
  },
  {
    "cluster": "indian_lang_pdfs_1.2_libtiff / tiff2pdf -",
    "original": "ShashvataSukhaNiketana_Hindi.pdf",
    "status": "processed"
  },
  {
    "cluster": "indian_lang_pdfs_1.2_libtiff / tiff2pdf -",
    "original": "Rochanamrita.pdf",
    "status": "processed"
  },
  {
    "cluster": "indian_lang_pdfs_1.2_libtiff / tiff2pdf -",
    "original": "KalyanaKalpaTaru.pdf",
    "status": "processed"
  },
  {
    "cluster": "english_epubs",
    "original": "The_Divine_Servitor.epub",
    "status": "processed"
  },
  {
    "cluster": "english_epubs",
    "original": "Heart_and_Halo.epub",
    "status": "processed"
  },
  {
    "cluster": "english_epubs",
    "original": "Srimad_Bhagavad-gita.epub",
    "status": "processed"
  },
  {
    "cluster": "english_pdfs_1.6_Acrobat Distiller 4.",
    "original": "Search_for_Sri_Krishna.pdf",
    "status": "processed"
  },
  {
    "cluster": "english_pdfs_1.6_Acrobat Distiller 4.",
    "original": "SubjectiveEvolution-1998.pdf",
    "status": "processed"
  },
  {
    "cluster": "english_pdfs_1.6_Acrobat Distiller 4.",
    "original": "GitaHiddenTreasure-2ndEdition.pdf",
    "status": "processed"
  },
  {
    "cluster": "english_pdfs_1.6_Adobe Acrobat 9.0 Im",
    "original": "ChaitanyaSaraswati-No1-VoiceOfSriChaitanyadev-scans.pdf",
    "status": "warning_low_content"
  },
  {
    "cluster": "english_pdfs_1.6_Adobe Acrobat 9.0 Im",
    "original": "BrahmaSamhita-Quintessence_scans.pdf",
    "status": "processed"
  },
  {
    "cluster": "english_pdfs_1.6_Adobe Acrobat 9.0 Im",
    "original": "GuardianOfDevotion-DumDumPark1986-BlueCover.pdf",
    "status": "processed"
  }
]